ecmwf/opendata/__init__.py
ecmwf/opendata/bufr.py
ecmwf/opendata/client.py
ecmwf/opendata/date.py
ecmwf/opendata/grib.py
ecmwf/opendata/urls.py
ecmwf_opendata-0.3.23.dist-info/licenses/LICENSE
ecmwf_opendata-0.3.23.dist-info/METADATA
ecmwf_opendata-0.3.23.dist-info/WHEEL
ecmwf_opendata-0.3.23.dist-info/top_level.txt
ecmwf_opendata-0.3.23.dist-info/zip-safe
ecmwf_opendata-0.3.23.dist-info/RECORD
